seatable_api_async/__init__.py
seatable_api_async/account_api.py
seatable_api_async/column.py
seatable_api_async/constants.py
seatable_api_async/exception.py
seatable_api_async/seatable_api.py
seatable_api_async/socket_io.py
seatable_api_async/utils.py
seatable_api_async-0.3.0.dist-info/WHEEL
seatable_api_async-0.3.0.dist-info/METADATA
seatable_api_async-0.3.0.dist-info/RECORD
