Metadata-Version: 2.3
Name: seatable-api-async
Version: 0.3.0
Summary: 异步版本的 SeaTable API Python 客户端，基于 aiohttp 实现
Author: bo-john, aifunc
Author-email: bo-john <boxiong74@gmail.com>, aifunc <tabshiftctrlalt@outlook.com>
License: Apache License 2.0
Requires-Dist: aiofiles>=24.1.0
Requires-Dist: aiohttp>=3.13.2
Requires-Dist: dotenv>=0.9.9
Requires-Dist: ply>=3.11
Requires-Dist: python-dateutil>=2.9.0.post0
Requires-Dist: python-socketio>=5.11.0
Requires-Python: >=3.13
Project-URL: Documentation, https://github.com/bo-john/seatable-api-async#readme
Project-URL: Homepage, https://github.com/bo-john/seatable-api-async
Project-URL: Issues, https://github.com/bo-john/seatable-api-async/issues
Project-URL: Repository, https://github.com/bo-john/seatable-api-async
